{
    "NewCompany1":{
        "companyCode":"new0.1",
        "companyName":"new company1",
        "shortCompanyName":"new short Company",
        "importExportCode":"1234",
        "CINnumber":"098",
        "MSMEnumber":"109"
    },
    "NewCompany2":{
        "companyCode":"new0.2",
        "companyName":"new company2",
        "shortCompanyName":"new short Company1",
        "importExportCode":"12345",
        "CINnumber":"0985",
        "MSMEnumber":"1095"
    },
    "costCentertype1":{
        "enterCode":"876",
        "enterName":"124124",
        "type":"",
        "OrgUnit":"DELTA TEXTILES INDIA PRIVATE LIMITED"
    },
    "costCentertype2":{
        "enterCode":"0987",
        "enterName":"test1234",
        "type":"",
        "OrgUnit":"DELTA TEXTILES INDIA PRIVATE LIMITED"
    }
    
    
}